zs_amazon_buddy/__init__.py
zs_amazon_buddy/amazon_buddy.py
zs_amazon_buddy/filter.py
zs_amazon_buddy/parser.py
zs_amazon_buddy/request.py
zs_amazon_buddy/rh.py
zs_amazon_buddy/enums/__init__.py
zs_amazon_buddy/enums/category.py
zs_amazon_buddy/enums/product_condition.py
zs_amazon_buddy/enums/sort_type.py
zs_amazon_buddy/models/__init__.py
zs_amazon_buddy/models/product.py
zs_amazon_buddy/models/review.py
zs_amazon_buddy/models/review_image.py
zs_amazon_buddy/models/search_result_product.py
zs_amazon_buddy-0.0.2.dist-info/METADATA
zs_amazon_buddy-0.0.2.dist-info/WHEEL
zs_amazon_buddy-0.0.2.dist-info/top_level.txt
zs_amazon_buddy-0.0.2.dist-info/RECORD
