Metadata-Version: 2.1
Name: zs-amazon-buddy
Version: 0.0.2
Summary: python wrapper for the amazon_buddy npm package
Home-page: https://github.com/Zselter07/py_amazon_buddy
Author: Kristof & Zselter
License: UNKNOWN
Platform: UNKNOWN
Classifier: Programming Language :: Python :: 3
Classifier: License :: OSI Approved :: MIT License
Classifier: Operating System :: OS Independent
Requires-Python: >=3.5
Requires-Dist: randomua
Requires-Dist: kcu
Requires-Dist: Unidecode
Requires-Dist: requests
Requires-Dist: jsoncodable
Requires-Dist: beautifulsoup4
